torch_mlp/__init__.py
torch_mlp/mlp.py
torch_mlp-0.1.0.dist-info/METADATA
torch_mlp-0.1.0.dist-info/WHEEL
torch_mlp-0.1.0.dist-info/top_level.txt
torch_mlp-0.1.0.dist-info/RECORD
