Metadata-Version: 2.1
Name: torch-mlp
Version: 0.1.0
Summary: A PyTorch package for creating multi-layer perceptrons (MLPs).
Author: RobDHess
Requires-Python: >=3.6
Provides-Extra: test
Requires-Dist: pytest ; extra == 'test'
